huscy/data_acquisition_methods/questionaire/__init__.py
huscy/data_acquisition_methods/questionaire/apps.py
huscy/data_acquisition_methods/questionaire/models.py
huscy/data_acquisition_methods/questionaire/serializer.py
huscy/data_acquisition_methods/questionaire/services.py
huscy/data_acquisition_methods/questionaire/urls.py
huscy/data_acquisition_methods/questionaire/views.py
huscy/data_acquisition_methods/questionaire/migrations/0001_initial.py
huscy/data_acquisition_methods/questionaire/migrations/__init__.py
huscy.data_acquisition_methods.questionaire-0.1.2a3.dist-info/METADATA
huscy.data_acquisition_methods.questionaire-0.1.2a3.dist-info/WHEEL
huscy.data_acquisition_methods.questionaire-0.1.2a3.dist-info/top_level.txt
huscy.data_acquisition_methods.questionaire-0.1.2a3.dist-info/RECORD
